mcp_cd_youth/__init__.py
mcp_cd_youth/server.py
mcp_knowledge_server-1.0.1.dist-info/METADATA
mcp_knowledge_server-1.0.1.dist-info/WHEEL
mcp_knowledge_server-1.0.1.dist-info/entry_points.txt
mcp_knowledge_server-1.0.1.dist-info/RECORD
