Metadata-Version: 2.4
Name: mcp-knowledge-server
Version: 1.0.1
Summary: MCP Server (STDIO) to fetch and parse Chengdu Youth Center activities
Author-email: fsyj123 <ycffsyj@gmail.com>
License-Expression: MIT
Keywords: chengdu,mcp,model context protocol,sse,youth,活动
Classifier: License :: OSI Approved :: MIT License
Classifier: Programming Language :: Python :: 3
Classifier: Programming Language :: Python :: 3 :: Only
Requires-Python: >=3.12
Requires-Dist: beautifulsoup4>=4.12
Requires-Dist: httpx>=0.26
Requires-Dist: lxml>=5.0
Requires-Dist: mcp[cli]>=1.2.0
Requires-Dist: pydantic>=2.7
Requires-Dist: starlette>=0.37
Requires-Dist: uvicorn>=0.29
